{
  "_fv": 85,
  "_type": "overlay",
  "definition": {
    "priority": "NORMAL",
    "components": [
      {
        "type": "image",
        "data": {
          "image": "ad00b8b2e3d13b6c300ec32c8f056846.png",
          "use1Xscale": true,
          "anchorPoint": "TOP_RIGHT",
          "x": 362,
          "y": 0,
          "locked": false
        }
      }
    ],
    "baseTexture": "",
    "overlayTarget": "Ingame",
    "displayCondition": {
      "name": "ITSHEREDisplayOverlayIngame"
    },
    "gridSettings": {
      "sx": 18,
      "sy": 18,
      "ox": 11,
      "oy": 15,
      "snapOnGrid": false
    }
  }
}